sentrystr-0.1.2.dist-info/METADATA
sentrystr-0.1.2.dist-info/WHEEL
sentrystr/__init__.py
sentrystr/_sentrystr.cpython-39-darwin.so
sentrystr/py.typed
sentrystr-0.1.2.dist-info/RECORD
