Metadata-Version: 2.4
Name: sentrystr
Version: 0.1.2
Classifier: Development Status :: 4 - Beta
Classifier: Intended Audience :: Developers
Classifier: License :: OSI Approved :: MIT License
Classifier: Programming Language :: Python :: 3
Classifier: Programming Language :: Python :: 3.8
Classifier: Programming Language :: Python :: 3.9
Classifier: Programming Language :: Python :: 3.10
Classifier: Programming Language :: Python :: 3.11
Classifier: Programming Language :: Python :: 3.12
Classifier: Programming Language :: Rust
Classifier: Topic :: Software Development :: Libraries :: Python Modules
Classifier: Topic :: System :: Monitoring
Requires-Dist: ruff>=0.1.0 ; extra == 'dev'
Requires-Dist: pre-commit>=3.0.0 ; extra == 'dev'
Requires-Dist: pytest>=7.0.0 ; extra == 'dev'
Requires-Dist: mypy>=1.0.0 ; extra == 'dev'
Provides-Extra: dev
Summary: Python bindings for SentryStr - a decentralized error tracking system using Nostr
Author: SentryStr Contributors
Requires-Python: >=3.8
Project-URL: Homepage, https://github.com/9qeklajc/sentrystr
Project-URL: Repository, https://github.com/9qeklajc/sentrystr
Project-URL: Issues, https://github.com/9qeklajc/sentrystr/issues
